tfseg/__init__.py
tfseg/model.py
tfseg/pair.py
tfseg/posseg.py
tfseg/silence_tensorflow.py
tfseg/test_cut.py
tfseg/chn_seg_albert/saved_model.pb
tfseg/chn_seg_albert/variables/variables.data-00000-of-00001
tfseg/chn_seg_albert/variables/variables.index
tfseg-1.1.0.dist-info/LICENSE
tfseg-1.1.0.dist-info/METADATA
tfseg-1.1.0.dist-info/WHEEL
tfseg-1.1.0.dist-info/top_level.txt
tfseg-1.1.0.dist-info/RECORD
